lensauto/__init__.py
lensauto/cli.py
lensauto/utils.py
lensauto-0.1.dist-info/METADATA
lensauto-0.1.dist-info/WHEEL
lensauto-0.1.dist-info/entry_points.txt
lensauto-0.1.dist-info/top_level.txt
lensauto-0.1.dist-info/RECORD
