Metadata-Version: 2.1
Name: lensauto
Version: 0.1
Requires-Dist: Click
